crawlers/__init__.py
crawlers/base.py
crawlers/chdbits.py
crawlers/exceptions.py
crawlers/fsm.py
crawlers/hdtime.py
crawlers/keepfrds.py
crawlers/lemonhd.py
crawlers/mteam.py
crawlers/opencd.py
crawlers/ourbits.py
crawlers/pterclub.py
crawlers/py.typed
crawlers/redleaves.py
crawlers/session.py
crawlers/ttg.py
crawlers/u2.py
crawlers/ubits.py
pt_crawler-1.0.22.dist-info/LICENSE
pt_crawler-1.0.22.dist-info/METADATA
pt_crawler-1.0.22.dist-info/WHEEL
pt_crawler-1.0.22.dist-info/top_level.txt
pt_crawler-1.0.22.dist-info/RECORD
