Metadata-Version: 2.1
Name: pt-crawler
Version: 1.0.22
Summary: a group of crawlers for private tracker website
Home-page: https://github.com/zqmillet/pt-crawler
Author: kinopico
Author-email: zqmillet@qq.com
License: UNKNOWN
Platform: UNKNOWN
License-File: LICENSE
Requires-Dist: lxml
Requires-Dist: pydantic
Requires-Dist: requests
